compyr/__init__.py
compyr/foo.py
compyr-0.0.3.dist-info/METADATA
compyr-0.0.3.dist-info/WHEEL
compyr-0.0.3.dist-info/licenses/LICENSE
compyr-0.0.3.dist-info/RECORD
