Metadata-Version: 2.4
Name: compyr
Version: 0.0.3
Summary: Testing framework for porting R functions over to Python
Project-URL: Homepage, https://apsocarras.github.io/compyr/
Project-URL: Repository, https://github.com/apsocarras/compyr
Project-URL: Documentation, https://apsocarras.github.io/compyr/
Author-email: Alexander Socarras <apsocarras.dev@gmail.com>
License-File: LICENSE
Keywords: python
Classifier: Intended Audience :: Developers
Classifier: Programming Language :: Python
Classifier: Programming Language :: Python :: 3
Classifier: Programming Language :: Python :: 3.9
Classifier: Programming Language :: Python :: 3.10
Classifier: Programming Language :: Python :: 3.11
Classifier: Programming Language :: Python :: 3.12
Classifier: Programming Language :: Python :: 3.13
Classifier: Topic :: Software Development :: Libraries :: Python Modules
Requires-Python: <4.0,>=3.9
